opscraper
